{
  "voiceId": "lincoln-project",
  "voiceName": "Lincoln Project",
  "collectedAt": "2026-03-21T11:37:34.393747",
  "date": "2026-03-21",
  "posts": [
    {
      "voiceId": "lincoln-project",
      "voiceName": "Lincoln Project",
      "platform": "x",
      "text": "If we don't use it then why beg other countries to help open it?\nIf we don't need it, then why send 2,500 troops to open it?\nIf we don't use it then why is it drastically affecting our gas prices at home?\n\n\nDisclose.tv (@disclosetv)\n\nNOW - Trump: \"We don't use the Strait [of Hormuz], the United States, we don't need it.\"\n\nVideo\n  \n\n\n\n\n\n\u2014 https://nitter.net/disclosetv/status/2035080075910001111#m",
      "sourceUrl": "https://x.com/ProjectLincoln/status/2035098810267959454",
      "timestamp": "2026-03-20T20:59:01+00:00",
      "type": "tweet"
    },
    {
      "voiceId": "lincoln-project",
      "voiceName": "Lincoln Project",
      "platform": "x",
      "text": "All because Republicans blocked a bill to fund TSA, FEMA, CISA, U.S. Coast Guard and countless other agencies.\n\nRepublicans control all 3 branches of government. They own this problem.\n\n\nBreaking911 (@Breaking911)\n\n\ud83e\udd2f TSA lines at LaGuardia International Airport in NYC stretching into hours-long waits due to the DHS shutdown.\n\n\ud83c\udfa5: @ScooterCasterNY\n\nVideo\n  \n\n\n\n\n\n\u2014 https://nitter.net/Breaking911/status/2034974109864530181#m",
      "sourceUrl": "https://x.com/ProjectLincoln/status/2035095282661106000",
      "timestamp": "2026-03-20T20:45:00+00:00",
      "type": "tweet"
    },
    {
      "voiceId": "lincoln-project",
      "voiceName": "Lincoln Project",
      "platform": "x",
      "text": "Watch the full episode here: piped.video/watch?v=3_ViTiNU\u2026",
      "sourceUrl": "https://x.com/ProjectLincoln/status/2035084337423557068",
      "timestamp": "2026-03-20T20:01:30+00:00",
      "type": "tweet"
    },
    {
      "voiceId": "lincoln-project",
      "voiceName": "Lincoln Project",
      "platform": "x",
      "text": "Trump's trigger-happy lawfare exposed his weakness: people talking about what he might've done with Epstein. Does he have the balls to sue now that he's scrambling to cover it all up?\n\nVideo",
      "sourceUrl": "https://x.com/ProjectLincoln/status/2035084151741673472",
      "timestamp": "2026-03-20T20:00:46+00:00",
      "type": "tweet"
    },
    {
      "voiceId": "lincoln-project",
      "voiceName": "Lincoln Project",
      "platform": "x",
      "text": ".@realDonaldTrump does this hurt?",
      "sourceUrl": "https://x.com/ProjectLincoln/status/2035068656351154342",
      "timestamp": "2026-03-20T18:59:12+00:00",
      "type": "tweet"
    },
    {
      "voiceId": "lincoln-project",
      "voiceName": "Lincoln Project",
      "platform": "x",
      "text": "\u2068\"Breaking records when it comes to unpopularity\"\u2069\n\nVideo",
      "sourceUrl": "https://x.com/ProjectLincoln/status/2035061492052001233",
      "timestamp": "2026-03-20T18:30:43+00:00",
      "type": "tweet"
    },
    {
      "voiceId": "lincoln-project",
      "voiceName": "Lincoln Project",
      "platform": "x",
      "text": "So alpha.\n\n\nAaron Rupar (@atrupar)\n\nTrump strains to get down into a chair\n\nVideo\n  \n\n\n\n\n\n\u2014 https://nitter.net/atrupar/status/2035014539842846725#m",
      "sourceUrl": "https://x.com/ProjectLincoln/status/2035023299265101828",
      "timestamp": "2026-03-20T15:58:58+00:00",
      "type": "tweet"
    },
    {
      "voiceId": "lincoln-project",
      "voiceName": "Lincoln Project",
      "platform": "x",
      "text": "The Trump-Epstein coverup keeps bringing us back to the same shady network of names and even MAGA is starting to notice. That's what terrifies Trump. Watch The LP Podcast here: piped.video/watch?v=3_ViTiNU\u2026",
      "sourceUrl": "https://x.com/ProjectLincoln/status/2034978506426179948",
      "timestamp": "2026-03-20T13:00:58+00:00",
      "type": "tweet"
    },
    {
      "voiceId": "lincoln-project",
      "voiceName": "Lincoln Project",
      "platform": "x",
      "text": "After selling us out to Putin over and over, Trump got less than nothing in return.\n\nVideo",
      "sourceUrl": "https://x.com/ProjectLincoln/status/2034789518612865261",
      "timestamp": "2026-03-20T00:30:00+00:00",
      "type": "tweet"
    },
    {
      "voiceId": "lincoln-project",
      "voiceName": "Lincoln Project",
      "platform": "x",
      "text": "Trump's War Is DESTROYING The Economy nitter.net/i/broadcasts/1nJOLEbDq\u2026",
      "sourceUrl": "https://x.com/ProjectLincoln/status/2034767396784021984",
      "timestamp": "2026-03-19T23:02:06+00:00",
      "type": "tweet"
    },
    {
      "voiceId": "lincoln-project",
      "voiceName": "Lincoln Project",
      "platform": "x",
      "text": "Thanks to Donald Trump, Russia's the real winner in this war.\n\nVideo\n  \n\n\n\n\nzerohedge (@zerohedge)\n\n*US AUTHORIZES DELIVERY, SALE OF CRUDE OIL FROM RUSSIA\n\n\n\n\u2014 https://nitter.net/zerohedge/status/2034708861161021865#m",
      "sourceUrl": "https://x.com/ProjectLincoln/status/2034753004549583249",
      "timestamp": "2026-03-19T22:04:54+00:00",
      "type": "tweet"
    },
    {
      "voiceId": "lincoln-project",
      "voiceName": "Lincoln Project",
      "platform": "x",
      "text": "TONIGHT: Trump\u2019s missile strikes abroad mean price-hikes at home. The Breakdown explains how Trump\u2019s Iranian war hurts American wallets at 7 PM EST: piped.video/watch?v=EfqpqTHq\u2026",
      "sourceUrl": "https://x.com/ProjectLincoln/status/2034744273602519158",
      "timestamp": "2026-03-19T21:30:13+00:00",
      "type": "tweet"
    },
    {
      "voiceId": "lincoln-project",
      "voiceName": "Lincoln Project",
      "platform": "x",
      "text": "Our President is Putin\u2019s easiest mark.\n\nVideo",
      "sourceUrl": "https://x.com/ProjectLincoln/status/2034646085789258235",
      "timestamp": "2026-03-19T15:00:03+00:00",
      "type": "tweet"
    },
    {
      "voiceId": "lincoln-project",
      "voiceName": "Lincoln Project",
      "platform": "x",
      "text": "Does this sound like someone who\u2019s in control?",
      "sourceUrl": "https://x.com/ProjectLincoln/status/2034657443657941439",
      "timestamp": "2026-03-19T15:45:11+00:00",
      "type": "tweet"
    },
    {
      "voiceId": "lincoln-project",
      "voiceName": "Lincoln Project",
      "platform": "youtube",
      "text": "Sue me, Donald. I dare you",
      "sourceUrl": "https://www.youtube.com/shorts/R_EBAm1xSgM",
      "timestamp": "2026-03-20T20:00:21+00:00",
      "type": "video_title"
    },
    {
      "voiceId": "lincoln-project",
      "voiceName": "Lincoln Project",
      "platform": "youtube",
      "text": "Trump &amp; Epstein's Shared Network Problem: This Isn\u2019t Coincidence Anymore",
      "sourceUrl": "https://www.youtube.com/watch?v=3_ViTiNUlok",
      "timestamp": "2026-03-20T08:00:06+00:00",
      "type": "video_title"
    },
    {
      "voiceId": "lincoln-project",
      "voiceName": "Lincoln Project",
      "platform": "youtube",
      "text": "Trump's War Is DESTROYING The Economy",
      "sourceUrl": "https://www.youtube.com/watch?v=EfqpqTHqCDs",
      "timestamp": "2026-03-20T00:00:51+00:00",
      "type": "video_title"
    },
    {
      "voiceId": "lincoln-project",
      "voiceName": "Lincoln Project",
      "platform": "youtube",
      "text": "NEW LINCOLN PROJECT AD: Traitors",
      "sourceUrl": "https://www.youtube.com/watch?v=lpj5kTv3lr4",
      "timestamp": "2026-03-19T15:21:57+00:00",
      "type": "video_title"
    },
    {
      "voiceId": "lincoln-project",
      "voiceName": "Lincoln Project",
      "platform": "youtube",
      "text": "Hegseth's vile orders",
      "sourceUrl": "https://www.youtube.com/shorts/M5N2mO4HBoE",
      "timestamp": "2026-03-18T20:30:09+00:00",
      "type": "video_title"
    },
    {
      "voiceId": "lincoln-project",
      "voiceName": "Lincoln Project",
      "platform": "youtube",
      "text": "Lt. General Mark Hertling On War In The Middle East",
      "sourceUrl": "https://www.youtube.com/shorts/58FWwxx1Tyw",
      "timestamp": "2026-03-17T19:50:47+00:00",
      "type": "video_title"
    },
    {
      "voiceId": "lincoln-project",
      "voiceName": "Lincoln Project",
      "platform": "youtube",
      "text": "War Is Not MAGA Cosplay: Lt. General Mark Hertling on the Iran War Dumpster Fire",
      "sourceUrl": "https://www.youtube.com/watch?v=MsCbTnVP51c",
      "timestamp": "2026-03-17T18:54:06+00:00",
      "type": "video_title"
    },
    {
      "voiceId": "lincoln-project",
      "voiceName": "Lincoln Project",
      "platform": "youtube",
      "text": "Coward",
      "sourceUrl": "https://www.youtube.com/watch?v=HWn64_WvZ5Q",
      "timestamp": "2026-03-13T17:56:12+00:00",
      "type": "video_title"
    },
    {
      "voiceId": "lincoln-project",
      "voiceName": "Lincoln Project",
      "platform": "youtube",
      "text": "Trump\u2019s Iran Clusterf*ck War Is The Ultimate Epstein Distraction",
      "sourceUrl": "https://www.youtube.com/watch?v=13kJ8j0wfEY",
      "timestamp": "2026-03-13T16:54:53+00:00",
      "type": "video_title"
    },
    {
      "voiceId": "lincoln-project",
      "voiceName": "Lincoln Project",
      "platform": "youtube",
      "text": "What Trump's Iran War Will Cost YOU",
      "sourceUrl": "https://www.youtube.com/watch?v=nIaC_riI-RI",
      "timestamp": "2026-03-13T00:12:59+00:00",
      "type": "video_title"
    },
    {
      "voiceId": "lincoln-project",
      "voiceName": "Lincoln Project",
      "platform": "bluesky",
      "text": "\u2068\"Breaking records when it comes to unpopularity\"\u2069",
      "sourceUrl": "https://bsky.app/profile/lincolnproject.us/post/3mhj5mypb5b2e",
      "timestamp": "2026-03-20T18:31:48.937830693Z",
      "type": "post"
    },
    {
      "voiceId": "lincoln-project",
      "voiceName": "Lincoln Project",
      "platform": "bluesky",
      "text": "The Trump-Epstein coverup keeps bringing us back to the same shady network of names and even MAGA is starting to notice. That's what terrifies Trump. Watch The LP Podcast here: https://www.youtube.com/watch?v=3_ViTiNUlok",
      "sourceUrl": "https://bsky.app/profile/lincolnproject.us/post/3mhil5b2qjw2u",
      "timestamp": "2026-03-20T13:00:53.552902531Z",
      "type": "post"
    },
    {
      "voiceId": "lincoln-project",
      "voiceName": "Lincoln Project",
      "platform": "bluesky",
      "text": "After selling us out to Putin over and over, Trump got less than nothing in return.\nhttps://www.youtube.com/watch?v=lpj5kTv3lr4",
      "sourceUrl": "https://bsky.app/profile/lincolnproject.us/post/3mhhb6pip6m2j",
      "timestamp": "2026-03-20T00:30:05.085519796Z",
      "type": "post"
    },
    {
      "voiceId": "lincoln-project",
      "voiceName": "Lincoln Project",
      "platform": "bluesky",
      "text": "TONIGHT: Trump\u2019s missile strikes abroad mean price-hikes at home. The Breakdown explains how Trump\u2019s Iranian war hurts American wallets at 7 PM EST: https://www.youtube.com/watch?v=EfqpqTHqCDs",
      "sourceUrl": "https://bsky.app/profile/lincolnproject.us/post/3mhgx4wyzp524",
      "timestamp": "2026-03-19T21:30:08.435132744Z",
      "type": "post"
    },
    {
      "voiceId": "lincoln-project",
      "voiceName": "Lincoln Project",
      "platform": "bluesky",
      "text": "Does this sound like someone who\u2019s in control?",
      "sourceUrl": "https://bsky.app/profile/lincolnproject.us/post/3mhgdtyanqh27",
      "timestamp": "2026-03-19T15:45:06.650128856Z",
      "type": "post"
    },
    {
      "voiceId": "lincoln-project",
      "voiceName": "Lincoln Project",
      "platform": "bluesky",
      "text": "Our President is Putin\u2019s easiest mark.",
      "sourceUrl": "https://bsky.app/profile/lincolnproject.us/post/3mhgbg4iin32n",
      "timestamp": "2026-03-19T15:01:33.826967925Z",
      "type": "post"
    },
    {
      "voiceId": "lincoln-project",
      "voiceName": "Lincoln Project",
      "platform": "bluesky",
      "text": "Fox: I'm really, really not happy about this inflation report. This does not look good to me. Prices were up by 3.11%. You're up 4.3% year-over-year.",
      "sourceUrl": "https://bsky.app/profile/lincolnproject.us/post/3mheifduqa227",
      "timestamp": "2026-03-18T22:01:04.703036448Z",
      "type": "post"
    },
    {
      "voiceId": "lincoln-project",
      "voiceName": "Lincoln Project",
      "platform": "bluesky",
      "text": "MAGA, didn\u2019t you think things would be better by now? What happened to \u201cday one\u201d?",
      "sourceUrl": "https://bsky.app/profile/lincolnproject.us/post/3mheeynpc3n2b",
      "timestamp": "2026-03-18T21:00:17.567441296Z",
      "type": "post"
    },
    {
      "voiceId": "lincoln-project",
      "voiceName": "Lincoln Project",
      "platform": "bluesky",
      "text": "Jerome Powell, President of the FED:\n\n\"Job gains have remained low. Inflation remains elevated\"\n\n\"High inflation largely reflects the price of goods, mainly due to tariffs\"  \n\n\"Short-term inflation expectations have risen in recent weeks due to the situation in the Middle East\"",
      "sourceUrl": "https://bsky.app/profile/lincolnproject.us/post/3mhee5s4caa2j",
      "timestamp": "2026-03-18T20:45:16.281642904Z",
      "type": "post"
    },
    {
      "voiceId": "lincoln-project",
      "voiceName": "Lincoln Project",
      "platform": "bluesky",
      "text": "JD Vance is a political shapeshifter, but becoming a cheerleader for unpopular foreign wars might be too much for his facade to embrace. MAGA is cracking. Watch Rick on MSNOW:",
      "sourceUrl": "https://bsky.app/profile/lincolnproject.us/post/3mhdnmfgcfx2e",
      "timestamp": "2026-03-18T14:01:50.219603156Z",
      "type": "post"
    },
    {
      "voiceId": "lincoln-project",
      "voiceName": "Lincoln Project",
      "platform": "bluesky",
      "text": "At this point Trump will need to release all of the Epstein files in order to distract from this war in Iran.",
      "sourceUrl": "https://bsky.app/profile/lincolnproject.us/post/3mhdiupxozg2b",
      "timestamp": "2026-03-18T12:37:00.96098612Z",
      "type": "post"
    },
    {
      "voiceId": "lincoln-project",
      "voiceName": "Lincoln Project",
      "platform": "bluesky",
      "text": "Join us today for a special Anniversary edition of Strategy Session LIVE w/ guest @mehdirhasan.bsky.social \nof @zeteo.com. He joins hosts @therickwilson.bsky.social \n@stuartpstevens.bsky.social & @joetrippi.bsky.social. Don't miss this important conversation- 5pm ET open.substack.com/live-stream/...",
      "sourceUrl": "https://bsky.app/profile/lincolnproject.us/post/3mhbnhl53es2a",
      "timestamp": "2026-03-17T18:53:48.998Z",
      "type": "post"
    },
    {
      "voiceId": "lincoln-project",
      "voiceName": "Lincoln Project",
      "platform": "bluesky",
      "text": "When JD Vance sold his soul to MAGA he didn't think he was going to have to defend another reckless gulf war, and he's not sure he wants his name on this dumpster fire. Watch Rick on MSNOW.",
      "sourceUrl": "https://bsky.app/profile/lincolnproject.us/post/3mhbsuu2eyq2d",
      "timestamp": "2026-03-17T20:30:43.224352243Z",
      "type": "post"
    },
    {
      "voiceId": "lincoln-project",
      "voiceName": "Lincoln Project",
      "platform": "bluesky",
      "text": "As the \"no new wars\" president plunges us into another foreign war without a plan, Lt. Gen. Mark Hertling shares what war in the gulf is really like, and how messy this will get for Trump and Hegseth: https://www.youtube.com/watch?v=MsCbTnVP51c",
      "sourceUrl": "https://bsky.app/profile/lincolnproject.us/post/3mhbnuklezm2n",
      "timestamp": "2026-03-17T19:01:04.600837839Z",
      "type": "post"
    },
    {
      "voiceId": "lincoln-project",
      "voiceName": "Lincoln Project",
      "platform": "bluesky",
      "text": "Hassett: If the war were to be extended, it wouldn't really disrupt the U.S. economy very much at all. It would hurt consumers, but that's really the last of our concerns right now.",
      "sourceUrl": "https://bsky.app/profile/lincolnproject.us/post/3mhb66nttvh2e",
      "timestamp": "2026-03-17T14:20:23.666499526Z",
      "type": "post"
    },
    {
      "voiceId": "lincoln-project",
      "voiceName": "Lincoln Project",
      "platform": "bluesky",
      "text": "Trump and Hegseth are desperate to control the press right now. Too bad this isn't the dictatorship they wished it was. Watch Rick on MSNOW",
      "sourceUrl": "https://bsky.app/profile/lincolnproject.us/post/3mhayvnmp6o2j",
      "timestamp": "2026-03-17T12:45:52.751406619Z",
      "type": "post"
    },
    {
      "voiceId": "lincoln-project",
      "voiceName": "Lincoln Project",
      "platform": "bluesky",
      "text": "ICYMI: You may not be able to afford gas or groceries but Trump and Kegsbreath don't care. They have schools to bomb and expensive dinners to enjoy. Watch The Breakdown here: https://www.youtube.com/watch?v=nIaC_riI-RI",
      "sourceUrl": "https://bsky.app/profile/lincolnproject.us/post/3mgzlobe7dq27",
      "timestamp": "2026-03-14T14:00:28.2162525Z",
      "type": "post"
    },
    {
      "voiceId": "lincoln-project",
      "voiceName": "Lincoln Project",
      "platform": "bluesky",
      "text": "JD Vance in NC: \"BBB is chock full of good things for this district and state\"\n\n(Big Beautiful Bill will cause 450,000 North Carolinians to lose health care coverage)",
      "sourceUrl": "https://bsky.app/profile/lincolnproject.us/post/3mgxnwb6d4r2m",
      "timestamp": "2026-03-13T19:35:24.457258133Z",
      "type": "post"
    },
    {
      "voiceId": "lincoln-project",
      "voiceName": "Lincoln Project",
      "platform": "tiktok",
      "text": "Trump's trigger-happy lawfare exposed his weakness: people talking about what he might've done with Epstein. Does he have the balls to sue now that he's scrambling to cover it all up? Watch the full episode on YouTube. Link in bio.",
      "sourceUrl": "https://www.tiktok.com/@thelincolnproject/video/7619430079793319182",
      "timestamp": "2026-03-20T20:00:16+00:00",
      "type": "video_caption"
    },
    {
      "voiceId": "lincoln-project",
      "voiceName": "Lincoln Project",
      "platform": "tiktok",
      "text": "Pete Hegseth is destroying our military values and punishing those who call out his war crimes. This isn't who we are. Watch the full interview on YouTube through the link in bio.",
      "sourceUrl": "https://www.tiktok.com/@thelincolnproject/video/7618695611767950606",
      "timestamp": "2026-03-18T20:30:06+00:00",
      "type": "video_caption"
    },
    {
      "voiceId": "lincoln-project",
      "voiceName": "Lincoln Project",
      "platform": "tiktok",
      "text": "You can\u2019t win without a plan, and you can\u2019t kill your way out of a war in the Middle East. Lt. General Mark Hertling joins the LP Pod to analyze the quagmire in Iran. Watch on YouTube through the link in bio.",
      "sourceUrl": "https://www.tiktok.com/@thelincolnproject/video/7618316810508668173",
      "timestamp": "2026-03-17T20:00:15+00:00",
      "type": "video_caption"
    },
    {
      "voiceId": "lincoln-project",
      "voiceName": "Lincoln Project",
      "platform": "tiktok",
      "text": "Young men are starting to realize that politics isn't just a social media trend, and they're getting hurt. This is a major voting group which Dems should fight to win back this November. Watch The Breakdown on YouTube through the link in bio.",
      "sourceUrl": "https://www.tiktok.com/@thelincolnproject/video/7617512755595054350",
      "timestamp": "2026-03-15T16:00:16+00:00",
      "type": "video_caption"
    },
    {
      "voiceId": "lincoln-project",
      "voiceName": "Lincoln Project",
      "platform": "tiktok",
      "text": "Trump's dismantling of our protections and squandering of resources is leaving us vulnerable, and at the worst possible time. Watch The Breakdown on YouTube through the link in our bio.",
      "sourceUrl": "https://www.tiktok.com/@thelincolnproject/video/7617141689341201677",
      "timestamp": "2026-03-14T16:00:21+00:00",
      "type": "video_caption"
    },
    {
      "voiceId": "lincoln-project",
      "voiceName": "Lincoln Project",
      "platform": "tiktok",
      "text": "Republicans are now realizing there is no exit ramp from this war, because there was never supposed to be. Trump just wanted the distraction, and doesn\u2019t care how many lives are lost. Watch the full episode through the link in bio.",
      "sourceUrl": "https://www.tiktok.com/@thelincolnproject/video/7616796447404608781",
      "timestamp": "2026-03-13T17:41:02+00:00",
      "type": "video_caption"
    },
    {
      "voiceId": "lincoln-project",
      "voiceName": "Lincoln Project",
      "platform": "tiktok",
      "text": "Firing anyone who was prosecuting Trump was the first domino in this destruction of our law and order in Trump 2.0. Catch JP Cooney on the LP Podcast on our YouTube. Link in bio.",
      "sourceUrl": "https://www.tiktok.com/@thelincolnproject/video/7615688188614528269",
      "timestamp": "2026-03-10T18:00:23+00:00",
      "type": "video_caption"
    },
    {
      "voiceId": "lincoln-project",
      "voiceName": "Lincoln Project",
      "platform": "tiktok",
      "text": "Policy debates will have to wait. Right now we need to save our democracy. Watch the full episode on the LP Podcast. Link in bio.",
      "sourceUrl": "https://www.tiktok.com/@thelincolnproject/video/7615533382331583757",
      "timestamp": "2026-03-10T08:00:17+00:00",
      "type": "video_caption"
    },
    {
      "voiceId": "lincoln-project",
      "voiceName": "Lincoln Project",
      "platform": "tiktok",
      "text": "She had to have seen this one coming... Watch the full episode of The Breakdown at the link in our bio.",
      "sourceUrl": "https://www.tiktok.com/@thelincolnproject/video/7614559573545897229",
      "timestamp": "2026-03-07T17:00:34+00:00",
      "type": "video_caption"
    }
  ],
  "topicSummary": {
    "uncategorized": [
      {
        "quote": "If we don't use it then why beg other countries to help open it?\nIf we don't need it, then why send 2,500 troops to open it?\nIf we don't use it then why is it drastically affecting our gas prices at h",
        "sourceUrl": "https://x.com/ProjectLincoln/status/2035098810267959454",
        "platform": "x",
        "timestamp": "2026-03-20T20:59:01+00:00"
      },
      {
        "quote": "All because Republicans blocked a bill to fund TSA, FEMA, CISA, U.S. Coast Guard and countless other agencies.\n\nRepublicans control all 3 branches of government. They own this problem.\n\n\nBreaking911 (",
        "sourceUrl": "https://x.com/ProjectLincoln/status/2035095282661106000",
        "platform": "x",
        "timestamp": "2026-03-20T20:45:00+00:00"
      },
      {
        "quote": "Watch the full episode here: piped.video/watch?v=3_ViTiNU\u2026",
        "sourceUrl": "https://x.com/ProjectLincoln/status/2035084337423557068",
        "platform": "x",
        "timestamp": "2026-03-20T20:01:30+00:00"
      },
      {
        "quote": "Trump's trigger-happy lawfare exposed his weakness: people talking about what he might've done with Epstein. Does he have the balls to sue now that he's scrambling to cover it all up?\n\nVideo",
        "sourceUrl": "https://x.com/ProjectLincoln/status/2035084151741673472",
        "platform": "x",
        "timestamp": "2026-03-20T20:00:46+00:00"
      },
      {
        "quote": ".@realDonaldTrump does this hurt?",
        "sourceUrl": "https://x.com/ProjectLincoln/status/2035068656351154342",
        "platform": "x",
        "timestamp": "2026-03-20T18:59:12+00:00"
      },
      {
        "quote": "\u2068\"Breaking records when it comes to unpopularity\"\u2069\n\nVideo",
        "sourceUrl": "https://x.com/ProjectLincoln/status/2035061492052001233",
        "platform": "x",
        "timestamp": "2026-03-20T18:30:43+00:00"
      },
      {
        "quote": "So alpha.\n\n\nAaron Rupar (@atrupar)\n\nTrump strains to get down into a chair\n\nVideo\n  \n\n\n\n\n\n\u2014 https://nitter.net/atrupar/status/2035014539842846725#m",
        "sourceUrl": "https://x.com/ProjectLincoln/status/2035023299265101828",
        "platform": "x",
        "timestamp": "2026-03-20T15:58:58+00:00"
      },
      {
        "quote": "The Trump-Epstein coverup keeps bringing us back to the same shady network of names and even MAGA is starting to notice. That's what terrifies Trump. Watch The LP Podcast here: piped.video/watch?v=3_V",
        "sourceUrl": "https://x.com/ProjectLincoln/status/2034978506426179948",
        "platform": "x",
        "timestamp": "2026-03-20T13:00:58+00:00"
      },
      {
        "quote": "After selling us out to Putin over and over, Trump got less than nothing in return.\n\nVideo",
        "sourceUrl": "https://x.com/ProjectLincoln/status/2034789518612865261",
        "platform": "x",
        "timestamp": "2026-03-20T00:30:00+00:00"
      },
      {
        "quote": "Trump's War Is DESTROYING The Economy nitter.net/i/broadcasts/1nJOLEbDq\u2026",
        "sourceUrl": "https://x.com/ProjectLincoln/status/2034767396784021984",
        "platform": "x",
        "timestamp": "2026-03-19T23:02:06+00:00"
      },
      {
        "quote": "Thanks to Donald Trump, Russia's the real winner in this war.\n\nVideo\n  \n\n\n\n\nzerohedge (@zerohedge)\n\n*US AUTHORIZES DELIVERY, SALE OF CRUDE OIL FROM RUSSIA\n\n\n\n\u2014 https://nitter.net/zerohedge/status/2034",
        "sourceUrl": "https://x.com/ProjectLincoln/status/2034753004549583249",
        "platform": "x",
        "timestamp": "2026-03-19T22:04:54+00:00"
      },
      {
        "quote": "TONIGHT: Trump\u2019s missile strikes abroad mean price-hikes at home. The Breakdown explains how Trump\u2019s Iranian war hurts American wallets at 7 PM EST: piped.video/watch?v=EfqpqTHq\u2026",
        "sourceUrl": "https://x.com/ProjectLincoln/status/2034744273602519158",
        "platform": "x",
        "timestamp": "2026-03-19T21:30:13+00:00"
      },
      {
        "quote": "Our President is Putin\u2019s easiest mark.\n\nVideo",
        "sourceUrl": "https://x.com/ProjectLincoln/status/2034646085789258235",
        "platform": "x",
        "timestamp": "2026-03-19T15:00:03+00:00"
      },
      {
        "quote": "Does this sound like someone who\u2019s in control?",
        "sourceUrl": "https://x.com/ProjectLincoln/status/2034657443657941439",
        "platform": "x",
        "timestamp": "2026-03-19T15:45:11+00:00"
      },
      {
        "quote": "Sue me, Donald. I dare you",
        "sourceUrl": "https://www.youtube.com/shorts/R_EBAm1xSgM",
        "platform": "youtube",
        "timestamp": "2026-03-20T20:00:21+00:00"
      },
      {
        "quote": "Trump &amp; Epstein's Shared Network Problem: This Isn\u2019t Coincidence Anymore",
        "sourceUrl": "https://www.youtube.com/watch?v=3_ViTiNUlok",
        "platform": "youtube",
        "timestamp": "2026-03-20T08:00:06+00:00"
      },
      {
        "quote": "Trump's War Is DESTROYING The Economy",
        "sourceUrl": "https://www.youtube.com/watch?v=EfqpqTHqCDs",
        "platform": "youtube",
        "timestamp": "2026-03-20T00:00:51+00:00"
      },
      {
        "quote": "NEW LINCOLN PROJECT AD: Traitors",
        "sourceUrl": "https://www.youtube.com/watch?v=lpj5kTv3lr4",
        "platform": "youtube",
        "timestamp": "2026-03-19T15:21:57+00:00"
      },
      {
        "quote": "Hegseth's vile orders",
        "sourceUrl": "https://www.youtube.com/shorts/M5N2mO4HBoE",
        "platform": "youtube",
        "timestamp": "2026-03-18T20:30:09+00:00"
      },
      {
        "quote": "Lt. General Mark Hertling On War In The Middle East",
        "sourceUrl": "https://www.youtube.com/shorts/58FWwxx1Tyw",
        "platform": "youtube",
        "timestamp": "2026-03-17T19:50:47+00:00"
      },
      {
        "quote": "War Is Not MAGA Cosplay: Lt. General Mark Hertling on the Iran War Dumpster Fire",
        "sourceUrl": "https://www.youtube.com/watch?v=MsCbTnVP51c",
        "platform": "youtube",
        "timestamp": "2026-03-17T18:54:06+00:00"
      },
      {
        "quote": "Coward",
        "sourceUrl": "https://www.youtube.com/watch?v=HWn64_WvZ5Q",
        "platform": "youtube",
        "timestamp": "2026-03-13T17:56:12+00:00"
      },
      {
        "quote": "Trump\u2019s Iran Clusterf*ck War Is The Ultimate Epstein Distraction",
        "sourceUrl": "https://www.youtube.com/watch?v=13kJ8j0wfEY",
        "platform": "youtube",
        "timestamp": "2026-03-13T16:54:53+00:00"
      },
      {
        "quote": "What Trump's Iran War Will Cost YOU",
        "sourceUrl": "https://www.youtube.com/watch?v=nIaC_riI-RI",
        "platform": "youtube",
        "timestamp": "2026-03-13T00:12:59+00:00"
      },
      {
        "quote": "\u2068\"Breaking records when it comes to unpopularity\"\u2069",
        "sourceUrl": "https://bsky.app/profile/lincolnproject.us/post/3mhj5mypb5b2e",
        "platform": "bluesky",
        "timestamp": "2026-03-20T18:31:48.937830693Z"
      },
      {
        "quote": "The Trump-Epstein coverup keeps bringing us back to the same shady network of names and even MAGA is starting to notice. That's what terrifies Trump. Watch The LP Podcast here: https://www.youtube.com",
        "sourceUrl": "https://bsky.app/profile/lincolnproject.us/post/3mhil5b2qjw2u",
        "platform": "bluesky",
        "timestamp": "2026-03-20T13:00:53.552902531Z"
      },
      {
        "quote": "After selling us out to Putin over and over, Trump got less than nothing in return.\nhttps://www.youtube.com/watch?v=lpj5kTv3lr4",
        "sourceUrl": "https://bsky.app/profile/lincolnproject.us/post/3mhhb6pip6m2j",
        "platform": "bluesky",
        "timestamp": "2026-03-20T00:30:05.085519796Z"
      },
      {
        "quote": "TONIGHT: Trump\u2019s missile strikes abroad mean price-hikes at home. The Breakdown explains how Trump\u2019s Iranian war hurts American wallets at 7 PM EST: https://www.youtube.com/watch?v=EfqpqTHqCDs",
        "sourceUrl": "https://bsky.app/profile/lincolnproject.us/post/3mhgx4wyzp524",
        "platform": "bluesky",
        "timestamp": "2026-03-19T21:30:08.435132744Z"
      },
      {
        "quote": "Does this sound like someone who\u2019s in control?",
        "sourceUrl": "https://bsky.app/profile/lincolnproject.us/post/3mhgdtyanqh27",
        "platform": "bluesky",
        "timestamp": "2026-03-19T15:45:06.650128856Z"
      },
      {
        "quote": "Our President is Putin\u2019s easiest mark.",
        "sourceUrl": "https://bsky.app/profile/lincolnproject.us/post/3mhgbg4iin32n",
        "platform": "bluesky",
        "timestamp": "2026-03-19T15:01:33.826967925Z"
      },
      {
        "quote": "Fox: I'm really, really not happy about this inflation report. This does not look good to me. Prices were up by 3.11%. You're up 4.3% year-over-year.",
        "sourceUrl": "https://bsky.app/profile/lincolnproject.us/post/3mheifduqa227",
        "platform": "bluesky",
        "timestamp": "2026-03-18T22:01:04.703036448Z"
      },
      {
        "quote": "MAGA, didn\u2019t you think things would be better by now? What happened to \u201cday one\u201d?",
        "sourceUrl": "https://bsky.app/profile/lincolnproject.us/post/3mheeynpc3n2b",
        "platform": "bluesky",
        "timestamp": "2026-03-18T21:00:17.567441296Z"
      },
      {
        "quote": "Jerome Powell, President of the FED:\n\n\"Job gains have remained low. Inflation remains elevated\"\n\n\"High inflation largely reflects the price of goods, mainly due to tariffs\"  \n\n\"Short-term inflation ex",
        "sourceUrl": "https://bsky.app/profile/lincolnproject.us/post/3mhee5s4caa2j",
        "platform": "bluesky",
        "timestamp": "2026-03-18T20:45:16.281642904Z"
      },
      {
        "quote": "JD Vance is a political shapeshifter, but becoming a cheerleader for unpopular foreign wars might be too much for his facade to embrace. MAGA is cracking. Watch Rick on MSNOW:",
        "sourceUrl": "https://bsky.app/profile/lincolnproject.us/post/3mhdnmfgcfx2e",
        "platform": "bluesky",
        "timestamp": "2026-03-18T14:01:50.219603156Z"
      },
      {
        "quote": "At this point Trump will need to release all of the Epstein files in order to distract from this war in Iran.",
        "sourceUrl": "https://bsky.app/profile/lincolnproject.us/post/3mhdiupxozg2b",
        "platform": "bluesky",
        "timestamp": "2026-03-18T12:37:00.96098612Z"
      },
      {
        "quote": "Join us today for a special Anniversary edition of Strategy Session LIVE w/ guest @mehdirhasan.bsky.social \nof @zeteo.com. He joins hosts @therickwilson.bsky.social \n@stuartpstevens.bsky.social & @joe",
        "sourceUrl": "https://bsky.app/profile/lincolnproject.us/post/3mhbnhl53es2a",
        "platform": "bluesky",
        "timestamp": "2026-03-17T18:53:48.998Z"
      },
      {
        "quote": "When JD Vance sold his soul to MAGA he didn't think he was going to have to defend another reckless gulf war, and he's not sure he wants his name on this dumpster fire. Watch Rick on MSNOW.",
        "sourceUrl": "https://bsky.app/profile/lincolnproject.us/post/3mhbsuu2eyq2d",
        "platform": "bluesky",
        "timestamp": "2026-03-17T20:30:43.224352243Z"
      },
      {
        "quote": "As the \"no new wars\" president plunges us into another foreign war without a plan, Lt. Gen. Mark Hertling shares what war in the gulf is really like, and how messy this will get for Trump and Hegseth:",
        "sourceUrl": "https://bsky.app/profile/lincolnproject.us/post/3mhbnuklezm2n",
        "platform": "bluesky",
        "timestamp": "2026-03-17T19:01:04.600837839Z"
      },
      {
        "quote": "Hassett: If the war were to be extended, it wouldn't really disrupt the U.S. economy very much at all. It would hurt consumers, but that's really the last of our concerns right now.",
        "sourceUrl": "https://bsky.app/profile/lincolnproject.us/post/3mhb66nttvh2e",
        "platform": "bluesky",
        "timestamp": "2026-03-17T14:20:23.666499526Z"
      },
      {
        "quote": "Trump and Hegseth are desperate to control the press right now. Too bad this isn't the dictatorship they wished it was. Watch Rick on MSNOW",
        "sourceUrl": "https://bsky.app/profile/lincolnproject.us/post/3mhayvnmp6o2j",
        "platform": "bluesky",
        "timestamp": "2026-03-17T12:45:52.751406619Z"
      },
      {
        "quote": "ICYMI: You may not be able to afford gas or groceries but Trump and Kegsbreath don't care. They have schools to bomb and expensive dinners to enjoy. Watch The Breakdown here: https://www.youtube.com/w",
        "sourceUrl": "https://bsky.app/profile/lincolnproject.us/post/3mgzlobe7dq27",
        "platform": "bluesky",
        "timestamp": "2026-03-14T14:00:28.2162525Z"
      },
      {
        "quote": "JD Vance in NC: \"BBB is chock full of good things for this district and state\"\n\n(Big Beautiful Bill will cause 450,000 North Carolinians to lose health care coverage)",
        "sourceUrl": "https://bsky.app/profile/lincolnproject.us/post/3mgxnwb6d4r2m",
        "platform": "bluesky",
        "timestamp": "2026-03-13T19:35:24.457258133Z"
      },
      {
        "quote": "Trump's trigger-happy lawfare exposed his weakness: people talking about what he might've done with Epstein. Does he have the balls to sue now that he's scrambling to cover it all up? Watch the full e",
        "sourceUrl": "https://www.tiktok.com/@thelincolnproject/video/7619430079793319182",
        "platform": "tiktok",
        "timestamp": "2026-03-20T20:00:16+00:00"
      },
      {
        "quote": "Pete Hegseth is destroying our military values and punishing those who call out his war crimes. This isn't who we are. Watch the full interview on YouTube through the link in bio.",
        "sourceUrl": "https://www.tiktok.com/@thelincolnproject/video/7618695611767950606",
        "platform": "tiktok",
        "timestamp": "2026-03-18T20:30:06+00:00"
      },
      {
        "quote": "You can\u2019t win without a plan, and you can\u2019t kill your way out of a war in the Middle East. Lt. General Mark Hertling joins the LP Pod to analyze the quagmire in Iran. Watch on YouTube through the link",
        "sourceUrl": "https://www.tiktok.com/@thelincolnproject/video/7618316810508668173",
        "platform": "tiktok",
        "timestamp": "2026-03-17T20:00:15+00:00"
      },
      {
        "quote": "Young men are starting to realize that politics isn't just a social media trend, and they're getting hurt. This is a major voting group which Dems should fight to win back this November. Watch The Bre",
        "sourceUrl": "https://www.tiktok.com/@thelincolnproject/video/7617512755595054350",
        "platform": "tiktok",
        "timestamp": "2026-03-15T16:00:16+00:00"
      },
      {
        "quote": "Trump's dismantling of our protections and squandering of resources is leaving us vulnerable, and at the worst possible time. Watch The Breakdown on YouTube through the link in our bio.",
        "sourceUrl": "https://www.tiktok.com/@thelincolnproject/video/7617141689341201677",
        "platform": "tiktok",
        "timestamp": "2026-03-14T16:00:21+00:00"
      },
      {
        "quote": "Republicans are now realizing there is no exit ramp from this war, because there was never supposed to be. Trump just wanted the distraction, and doesn\u2019t care how many lives are lost. Watch the full e",
        "sourceUrl": "https://www.tiktok.com/@thelincolnproject/video/7616796447404608781",
        "platform": "tiktok",
        "timestamp": "2026-03-13T17:41:02+00:00"
      },
      {
        "quote": "Firing anyone who was prosecuting Trump was the first domino in this destruction of our law and order in Trump 2.0. Catch JP Cooney on the LP Podcast on our YouTube. Link in bio.",
        "sourceUrl": "https://www.tiktok.com/@thelincolnproject/video/7615688188614528269",
        "platform": "tiktok",
        "timestamp": "2026-03-10T18:00:23+00:00"
      },
      {
        "quote": "Policy debates will have to wait. Right now we need to save our democracy. Watch the full episode on the LP Podcast. Link in bio.",
        "sourceUrl": "https://www.tiktok.com/@thelincolnproject/video/7615533382331583757",
        "platform": "tiktok",
        "timestamp": "2026-03-10T08:00:17+00:00"
      },
      {
        "quote": "She had to have seen this one coming... Watch the full episode of The Breakdown at the link in our bio.",
        "sourceUrl": "https://www.tiktok.com/@thelincolnproject/video/7614559573545897229",
        "platform": "tiktok",
        "timestamp": "2026-03-07T17:00:34+00:00"
      }
    ]
  }
}