{
  "voiceId": "meghan-mccain",
  "voiceName": "Meghan McCain",
  "collectedAt": "2026-03-11T23:00:33.711965",
  "date": "2026-03-11",
  "posts": [
    {
      "voiceId": "meghan-mccain",
      "voiceName": "Meghan McCain",
      "platform": "x",
      "text": "My understanding is this food was for the men and women in our armed forces - and as far as I'm concerned they can have caviar and champagne every day given they are putting their literal lives on the line for our protection.\n\n\nMediaite (@Mediaite)\n\nPete Hegseth\u2019s Defense Department Blew $22M On Steak and Lobster in a Single Month, Watchdog Claims\nmediaite.com/politics/pete-h\u2026\n\nCommunity note: Important context, members of the United States military have been served \u201cSurf and Turf\u201d for decades, ",
      "sourceUrl": "https://x.com/MeghanMcCain/status/2031772066182009336",
      "timestamp": "2026-03-11T16:39:43+00:00",
      "type": "tweet"
    },
    {
      "voiceId": "meghan-mccain",
      "voiceName": "Meghan McCain",
      "platform": "x",
      "text": "Shut the fuck up Sheryl Sandberg. I don't even know why you're still talking given the amount of abject lies and insanity you tried to sell my generation.\n\n\nPeople (@people)\n\nLean In's Sheryl Sandberg Says Tradwives Could Be 'Very Detrimental to Women,' Even If by Accident (Exclusive) people.com/sheryl-sandberg-t\u2026\n\n\n\n\n\u2014 https://nitter.net/people/status/2031504402175947167#m",
      "sourceUrl": "https://x.com/MeghanMcCain/status/2031773456727994612",
      "timestamp": "2026-03-11T16:45:15+00:00",
      "type": "tweet"
    },
    {
      "voiceId": "meghan-mccain",
      "voiceName": "Meghan McCain",
      "platform": "x",
      "text": "He was not, actually.\n\n\nMikey (@GaintrustMikey)\n\nHe was at your wedding, Meghan.\n\n(This is a callback joke)\n\n\n\n\u2014 https://nitter.net/GaintrustMikey/status/2031713209959272584#m",
      "sourceUrl": "https://x.com/MeghanMcCain/status/2031714509010731232",
      "timestamp": "2026-03-11T12:51:01+00:00",
      "type": "tweet"
    },
    {
      "voiceId": "meghan-mccain",
      "voiceName": "Meghan McCain",
      "platform": "x",
      "text": "Nothing like a single, childless, septuagenarian telling American mothers to send their children to go possibly die in a war.\n\n\nAF Post (@AFpost)\n\nSen. Lindsey Graham: \u201cI'm going back to South Carolina and asking them to send their sons and daughters over to the MidEast.\u201d \n\nFollow: @AFpost\n\nVideo\n  \n\n\n\n\n\u2014 https://nitter.net/AFpost/status/2031227161672298867#m",
      "sourceUrl": "https://x.com/MeghanMcCain/status/2031475975574163541",
      "timestamp": "2026-03-10T21:03:10+00:00",
      "type": "tweet"
    },
    {
      "voiceId": "meghan-mccain",
      "voiceName": "Meghan McCain",
      "platform": "x",
      "text": "Please join me in sending prayers, strength and light to Liz, her family, loved ones and baby Solomon. I do not understand the will of God and don\u2019t pretend to.\n\n\nLiz Wolfe (@LizWolfeReason)\n\nKing Solomon died yesterday at two and a half months old. We loved him really well, and we don't have any regrets. We got nine days at home with him after 61 days in the NICU. Nine will never feel like enough, but we must accept what is given to us\u2013\u2013we were never in control.\n\nLet's take stock of all God's m",
      "sourceUrl": "https://x.com/MeghanMcCain/status/2031417250956067085",
      "timestamp": "2026-03-10T17:09:49+00:00",
      "type": "tweet"
    },
    {
      "voiceId": "meghan-mccain",
      "voiceName": "Meghan McCain",
      "platform": "x",
      "text": "About to join my friends @GaydosKTAR &amp; @TheBruceStJames on @OutspokenKTAR at the top of the hour for \"Monday's with Meghan\". Tune into @KTAR923 Arizonans!",
      "sourceUrl": "https://x.com/MeghanMcCain/status/2031127765785661533",
      "timestamp": "2026-03-09T21:59:30+00:00",
      "type": "tweet"
    },
    {
      "voiceId": "meghan-mccain",
      "voiceName": "Meghan McCain",
      "platform": "x",
      "text": "One of my great childhood fears come to life\u2026\n\n\nDan Nowicki (@dannowicki)\n\n\"Quicksand warning for Arizona\u2019s Glen Canyon near Lake Powell.\" (via @Jflevin) azcentral.com/story/news/loc\u2026\n\n\n\n\n\u2014 https://nitter.net/dannowicki/status/2031103368358408284#m",
      "sourceUrl": "https://x.com/MeghanMcCain/status/2031122505033724209",
      "timestamp": "2026-03-09T21:38:36+00:00",
      "type": "tweet"
    },
    {
      "voiceId": "meghan-mccain",
      "voiceName": "Meghan McCain",
      "platform": "x",
      "text": "Keep the fat comments coming because I'm sorry to disappoint so many of you, I will not be going on any of the ozempic shots despite just having my third child.\n\nNo judgment to those that do, but I just don't believe in the concept of a magic shot - everything has a price.\n\n*I also don't want my face to change.",
      "sourceUrl": "https://x.com/MeghanMcCain/status/2031096833372573870",
      "timestamp": "2026-03-09T19:56:35+00:00",
      "type": "tweet"
    }
  ],
  "topicSummary": {
    "uncategorized": [
      {
        "quote": "My understanding is this food was for the men and women in our armed forces - and as far as I'm concerned they can have caviar and champagne every day given they are putting their literal lives on the",
        "sourceUrl": "https://x.com/MeghanMcCain/status/2031772066182009336",
        "platform": "x",
        "timestamp": "2026-03-11T16:39:43+00:00"
      },
      {
        "quote": "Shut the fuck up Sheryl Sandberg. I don't even know why you're still talking given the amount of abject lies and insanity you tried to sell my generation.\n\n\nPeople (@people)\n\nLean In's Sheryl Sandberg",
        "sourceUrl": "https://x.com/MeghanMcCain/status/2031773456727994612",
        "platform": "x",
        "timestamp": "2026-03-11T16:45:15+00:00"
      },
      {
        "quote": "He was not, actually.\n\n\nMikey (@GaintrustMikey)\n\nHe was at your wedding, Meghan.\n\n(This is a callback joke)\n\n\n\n\u2014 https://nitter.net/GaintrustMikey/status/2031713209959272584#m",
        "sourceUrl": "https://x.com/MeghanMcCain/status/2031714509010731232",
        "platform": "x",
        "timestamp": "2026-03-11T12:51:01+00:00"
      },
      {
        "quote": "Nothing like a single, childless, septuagenarian telling American mothers to send their children to go possibly die in a war.\n\n\nAF Post (@AFpost)\n\nSen. Lindsey Graham: \u201cI'm going back to South Carolin",
        "sourceUrl": "https://x.com/MeghanMcCain/status/2031475975574163541",
        "platform": "x",
        "timestamp": "2026-03-10T21:03:10+00:00"
      },
      {
        "quote": "Please join me in sending prayers, strength and light to Liz, her family, loved ones and baby Solomon. I do not understand the will of God and don\u2019t pretend to.\n\n\nLiz Wolfe (@LizWolfeReason)\n\nKing Sol",
        "sourceUrl": "https://x.com/MeghanMcCain/status/2031417250956067085",
        "platform": "x",
        "timestamp": "2026-03-10T17:09:49+00:00"
      },
      {
        "quote": "About to join my friends @GaydosKTAR &amp; @TheBruceStJames on @OutspokenKTAR at the top of the hour for \"Monday's with Meghan\". Tune into @KTAR923 Arizonans!",
        "sourceUrl": "https://x.com/MeghanMcCain/status/2031127765785661533",
        "platform": "x",
        "timestamp": "2026-03-09T21:59:30+00:00"
      },
      {
        "quote": "One of my great childhood fears come to life\u2026\n\n\nDan Nowicki (@dannowicki)\n\n\"Quicksand warning for Arizona\u2019s Glen Canyon near Lake Powell.\" (via @Jflevin) azcentral.com/story/news/loc\u2026\n\n\n\n\n\u2014 https://ni",
        "sourceUrl": "https://x.com/MeghanMcCain/status/2031122505033724209",
        "platform": "x",
        "timestamp": "2026-03-09T21:38:36+00:00"
      },
      {
        "quote": "Keep the fat comments coming because I'm sorry to disappoint so many of you, I will not be going on any of the ozempic shots despite just having my third child.\n\nNo judgment to those that do, but I ju",
        "sourceUrl": "https://x.com/MeghanMcCain/status/2031096833372573870",
        "platform": "x",
        "timestamp": "2026-03-09T19:56:35+00:00"
      }
    ]
  }
}