{
  "voiceId": "bill-maher",
  "voiceName": "Bill Maher",
  "collectedAt": "2026-03-14T14:38:17.259847",
  "date": "2026-03-14",
  "posts": [
    {
      "voiceId": "bill-maher",
      "voiceName": "Bill Maher",
      "platform": "x",
      "text": "Hollywood isn't a secret cabal of racists; it's a secret cabal of people terrified of looking like racists. #OscarsSoWrong\n\nVideo",
      "sourceUrl": "https://x.com/billmaher/status/2032659311265198405",
      "timestamp": "2026-03-14T03:25:19+00:00",
      "type": "tweet",
      "topic": "celebrity-entertainment",
      "relevance": "medium",
      "stance": "strong",
      "quote": "Hollywood isn't a secret cabal of racists; it's a secret cabal of people terrified of looking like racists. #OscarsSoWrong\n\nVideo"
    },
    {
      "voiceId": "bill-maher",
      "voiceName": "Bill Maher",
      "platform": "x",
      "text": "It's Friday the 13th! I'm not superstitious, but if you're in Tehran, don't walk under a leader.\n\nVideo",
      "sourceUrl": "https://x.com/billmaher/status/2032659152154263797",
      "timestamp": "2026-03-14T03:24:41+00:00",
      "type": "tweet",
      "topic": "iran-conflict",
      "relevance": "high",
      "stance": "lean",
      "quote": "It's Friday the 13th! I'm not superstitious, but if you're in Tehran, don't walk under a leader.\n\nVideo"
    },
    {
      "voiceId": "bill-maher",
      "voiceName": "Bill Maher",
      "platform": "x",
      "text": "Trump fired Kristi Noem. He did it by tweet while she was giving a speech. She never saw it coming. Now she knows how her dog felt.\n\nVideo",
      "sourceUrl": "https://x.com/billmaher/status/2030133685346054651",
      "timestamp": "2026-03-07T04:09:23+00:00",
      "type": "tweet",
      "topic": "trump-administration",
      "relevance": "high",
      "stance": "strong",
      "quote": "Trump fired Kristi Noem. He did it by tweet while she was giving a speech. She never saw it coming. Now she knows how her dog felt.\n\nVideo"
    },
    {
      "voiceId": "bill-maher",
      "voiceName": "Bill Maher",
      "platform": "x",
      "text": "Western values are not about oppression.\n\nVideo",
      "sourceUrl": "https://x.com/billmaher/status/2027454417805709675",
      "timestamp": "2026-02-27T18:42:56+00:00",
      "type": "tweet",
      "topic": "culture-war",
      "relevance": "medium",
      "stance": "strong",
      "quote": "Western values are not about oppression.\n\nVideo"
    },
    {
      "voiceId": "bill-maher",
      "voiceName": "Bill Maher",
      "platform": "x",
      "text": "Democrats don't eat babies.\n\nVideo",
      "sourceUrl": "https://x.com/billmaher/status/2026718980027904499",
      "timestamp": "2026-02-25T18:00:34+00:00",
      "type": "tweet",
      "topic": "culture-war",
      "relevance": "medium",
      "stance": "strong",
      "quote": "Democrats don't eat babies.\n\nVideo"
    },
    {
      "voiceId": "bill-maher",
      "voiceName": "Bill Maher",
      "platform": "youtube",
      "text": "New Rule: Oscars So Wrong | Real Time with Bill Maher (HBO)",
      "sourceUrl": "https://www.youtube.com/watch?v=7nHupEb2NL0",
      "timestamp": "2026-03-14T03:00:00+00:00",
      "type": "video_title",
      "topic": "celebrity-entertainment",
      "relevance": "medium",
      "stance": "strong",
      "quote": "New Rule: Oscars So Wrong | Real Time with Bill Maher (HBO)"
    },
    {
      "voiceId": "bill-maher",
      "voiceName": "Bill Maher",
      "platform": "youtube",
      "text": "Rewriting History | Real Time with Bill Maher (HBO)",
      "sourceUrl": "https://www.youtube.com/watch?v=Sd4Y0ozYkFw",
      "timestamp": "2026-03-14T03:00:00+00:00",
      "type": "video_title",
      "topic": "culture-war",
      "relevance": "medium",
      "stance": "lean",
      "quote": "Rewriting History | Real Time with Bill Maher (HBO)"
    },
    {
      "voiceId": "bill-maher",
      "voiceName": "Bill Maher",
      "platform": "youtube",
      "text": "Overtime with Bill Maher: Anthony Scaramucci, Lloyd Blankfein (HBO)",
      "sourceUrl": "https://www.youtube.com/watch?v=ixDs6Hht6sI",
      "timestamp": "2026-03-14T03:00:00+00:00",
      "type": "video_title",
      "topic": "trump-administration",
      "relevance": "high",
      "stance": "lean",
      "quote": "Overtime with Bill Maher: Anthony Scaramucci, Lloyd Blankfein (HBO)"
    },
    {
      "voiceId": "bill-maher",
      "voiceName": "Bill Maher",
      "platform": "youtube",
      "text": "Overtime with Bill Maher: Sen. Adam Schiff, Don Lemon, Annabelle Gurwitch (HBO)",
      "sourceUrl": "https://www.youtube.com/watch?v=42WhjZc5hp8",
      "timestamp": "2026-03-07T04:00:00+00:00",
      "type": "video_title",
      "topic": "trump-administration",
      "relevance": "high",
      "stance": "lean",
      "quote": "Overtime with Bill Maher: Sen. Adam Schiff, Don Lemon, Annabelle Gurwitch (HBO)"
    },
    {
      "voiceId": "bill-maher",
      "voiceName": "Bill Maher",
      "platform": "youtube",
      "text": "Monologue: Truth Ache | Real Time with Bill Maher (HBO)",
      "sourceUrl": "https://www.youtube.com/watch?v=gv8w50WxH5o",
      "timestamp": "2026-03-07T04:00:00+00:00",
      "type": "video_title",
      "topic": "media-press",
      "relevance": "medium",
      "stance": "lean",
      "quote": "Monologue: Truth Ache | Real Time with Bill Maher (HBO)"
    },
    {
      "voiceId": "bill-maher",
      "voiceName": "Bill Maher",
      "platform": "youtube",
      "text": "New Rule: Trump Estrangement Syndrome | Real Time with Bill Maher (HBO)",
      "sourceUrl": "https://www.youtube.com/watch?v=sbGZSOk_CvU",
      "timestamp": "2026-03-07T04:00:00+00:00",
      "type": "video_title",
      "topic": "culture-war",
      "relevance": "medium",
      "stance": "lean",
      "quote": "New Rule: Trump Estrangement Syndrome | Real Time with Bill Maher (HBO)"
    },
    {
      "voiceId": "bill-maher",
      "voiceName": "Bill Maher",
      "platform": "youtube",
      "text": "Overtime with Bill Maher: Lauren Boebert, James Talarico (HBO)",
      "sourceUrl": "https://www.youtube.com/watch?v=s2TWrUXSLmw",
      "timestamp": "2026-02-21T06:27:46+00:00",
      "type": "video_title",
      "topic": "religion-faith",
      "relevance": "medium",
      "stance": "lean",
      "quote": "Overtime with Bill Maher: Lauren Boebert, James Talarico (HBO)"
    },
    {
      "voiceId": "bill-maher",
      "voiceName": "Bill Maher",
      "platform": "youtube",
      "text": "James Talarico and Lauren Boebert Debate Church &amp; State | Real Time with Bill Maher (HBO)",
      "sourceUrl": "https://www.youtube.com/watch?v=iDb3RsCsg1c",
      "timestamp": "2026-02-21T06:11:28+00:00",
      "type": "video_title",
      "topic": "religion-faith",
      "relevance": "medium",
      "stance": "lean",
      "quote": "James Talarico and Lauren Boebert Debate Church &amp; State | Real Time with Bill Maher (HBO)"
    },
    {
      "voiceId": "bill-maher",
      "voiceName": "Bill Maher",
      "platform": "youtube",
      "text": "New Rule: The King's Speech | Real Time with Bill Maher (HBO)",
      "sourceUrl": "https://www.youtube.com/watch?v=3KuNI0V3JkM",
      "timestamp": "2026-02-21T04:00:00+00:00",
      "type": "video_title",
      "topic": "free-speech-censorship",
      "relevance": "medium",
      "stance": "lean",
      "quote": "New Rule: The King's Speech | Real Time with Bill Maher (HBO)"
    },
    {
      "voiceId": "bill-maher",
      "voiceName": "Bill Maher",
      "platform": "youtube",
      "text": "What a Girl Wants (Taylor's Version) | Real Time with Bill Maher (HBO)",
      "sourceUrl": "https://www.youtube.com/watch?v=LyvRScV-Y-E",
      "timestamp": "2026-02-14T04:00:00+00:00",
      "type": "video_title",
      "topic": "celebrity-entertainment",
      "relevance": "medium",
      "stance": "lean",
      "quote": "What a Girl Wants (Taylor's Version) | Real Time with Bill Maher (HBO)"
    }
  ],
  "topicSummary": {
    "celebrity-entertainment": [
      {
        "quote": "Hollywood isn't a secret cabal of racists; it's a secret cabal of people terrified of looking like racists. #OscarsSoWrong\n\nVideo",
        "sourceUrl": "https://x.com/billmaher/status/2032659311265198405",
        "platform": "x",
        "timestamp": "2026-03-14T03:25:19+00:00"
      },
      {
        "quote": "New Rule: Oscars So Wrong | Real Time with Bill Maher (HBO)",
        "sourceUrl": "https://www.youtube.com/watch?v=7nHupEb2NL0",
        "platform": "youtube",
        "timestamp": "2026-03-14T03:00:00+00:00"
      },
      {
        "quote": "What a Girl Wants (Taylor's Version) | Real Time with Bill Maher (HBO)",
        "sourceUrl": "https://www.youtube.com/watch?v=LyvRScV-Y-E",
        "platform": "youtube",
        "timestamp": "2026-02-14T04:00:00+00:00"
      }
    ],
    "iran-conflict": [
      {
        "quote": "It's Friday the 13th! I'm not superstitious, but if you're in Tehran, don't walk under a leader.\n\nVideo",
        "sourceUrl": "https://x.com/billmaher/status/2032659152154263797",
        "platform": "x",
        "timestamp": "2026-03-14T03:24:41+00:00"
      }
    ],
    "trump-administration": [
      {
        "quote": "Trump fired Kristi Noem. He did it by tweet while she was giving a speech. She never saw it coming. Now she knows how her dog felt.\n\nVideo",
        "sourceUrl": "https://x.com/billmaher/status/2030133685346054651",
        "platform": "x",
        "timestamp": "2026-03-07T04:09:23+00:00"
      },
      {
        "quote": "Overtime with Bill Maher: Anthony Scaramucci, Lloyd Blankfein (HBO)",
        "sourceUrl": "https://www.youtube.com/watch?v=ixDs6Hht6sI",
        "platform": "youtube",
        "timestamp": "2026-03-14T03:00:00+00:00"
      },
      {
        "quote": "Overtime with Bill Maher: Sen. Adam Schiff, Don Lemon, Annabelle Gurwitch (HBO)",
        "sourceUrl": "https://www.youtube.com/watch?v=42WhjZc5hp8",
        "platform": "youtube",
        "timestamp": "2026-03-07T04:00:00+00:00"
      }
    ],
    "culture-war": [
      {
        "quote": "Western values are not about oppression.\n\nVideo",
        "sourceUrl": "https://x.com/billmaher/status/2027454417805709675",
        "platform": "x",
        "timestamp": "2026-02-27T18:42:56+00:00"
      },
      {
        "quote": "Democrats don't eat babies.\n\nVideo",
        "sourceUrl": "https://x.com/billmaher/status/2026718980027904499",
        "platform": "x",
        "timestamp": "2026-02-25T18:00:34+00:00"
      },
      {
        "quote": "Rewriting History | Real Time with Bill Maher (HBO)",
        "sourceUrl": "https://www.youtube.com/watch?v=Sd4Y0ozYkFw",
        "platform": "youtube",
        "timestamp": "2026-03-14T03:00:00+00:00"
      },
      {
        "quote": "New Rule: Trump Estrangement Syndrome | Real Time with Bill Maher (HBO)",
        "sourceUrl": "https://www.youtube.com/watch?v=sbGZSOk_CvU",
        "platform": "youtube",
        "timestamp": "2026-03-07T04:00:00+00:00"
      }
    ],
    "media-press": [
      {
        "quote": "Monologue: Truth Ache | Real Time with Bill Maher (HBO)",
        "sourceUrl": "https://www.youtube.com/watch?v=gv8w50WxH5o",
        "platform": "youtube",
        "timestamp": "2026-03-07T04:00:00+00:00"
      }
    ],
    "religion-faith": [
      {
        "quote": "Overtime with Bill Maher: Lauren Boebert, James Talarico (HBO)",
        "sourceUrl": "https://www.youtube.com/watch?v=s2TWrUXSLmw",
        "platform": "youtube",
        "timestamp": "2026-02-21T06:27:46+00:00"
      },
      {
        "quote": "James Talarico and Lauren Boebert Debate Church &amp; State | Real Time with Bill Maher (HBO)",
        "sourceUrl": "https://www.youtube.com/watch?v=iDb3RsCsg1c",
        "platform": "youtube",
        "timestamp": "2026-02-21T06:11:28+00:00"
      }
    ],
    "free-speech-censorship": [
      {
        "quote": "New Rule: The King's Speech | Real Time with Bill Maher (HBO)",
        "sourceUrl": "https://www.youtube.com/watch?v=3KuNI0V3JkM",
        "platform": "youtube",
        "timestamp": "2026-02-21T04:00:00+00:00"
      }
    ]
  }
}